{
  "version": "7",
  "dialect": "postgresql",
  "entries": [
    {
      "idx": 0,
      "version": "7",
      "when": 1774360621833,
      "tag": "0000_daffy_reavers",
      "breakpoints": true
    },
    {
      "idx": 1,
      "version": "7",
      "when": 1774371965654,
      "tag": "0001_loud_bruce_banner",
      "breakpoints": true
    },
    {
      "idx": 2,
      "version": "7",
      "when": 1774374734379,
      "tag": "0002_sweet_cobalt_man",
      "breakpoints": true
    },
    {
      "idx": 3,
      "version": "7",
      "when": 1775487356124,
      "tag": "0003_broken_omega_sentinel",
      "breakpoints": true
    },
    {
      "idx": 4,
      "version": "7",
      "when": 1775559592652,
      "tag": "0004_sad_sharon_ventura",
      "breakpoints": true
    },
    {
      "idx": 5,
      "version": "7",
      "when": 1775660306385,
      "tag": "0005_conscious_rictor",
      "breakpoints": true
    },
    {
      "idx": 6,
      "version": "7",
      "when": 1777234519154,
      "tag": "0006_add_duels",
      "breakpoints": true
    }
  ]
}